setup.py
webpage_reader/__init__.py
webpage_reader/html5.py
webpage_reader.egg-info/PKG-INFO
webpage_reader.egg-info/SOURCES.txt
webpage_reader.egg-info/dependency_links.txt
webpage_reader.egg-info/requires.txt
webpage_reader.egg-info/top_level.txt