Metadata-Version: 1.0
Name: webpage-reader
Version: 0.0.4
Summary: Reads a webpage and extracts the information out of it, based on the HTML5 tags/classes 
Home-page: https://github.com/invanatech/webpage-reader
Author: rrmerugu
Author-email: rrmerugu@gmail.com
License: MIT License
Platform: UNKNOWN
